{
  "type": "forge:conditional",
  "recipes": [
    {
      "conditions": [
        {
          "type": "collectorsreap:enabled",
          "value": "portobello_quiche"
        }
      ],
      "recipe": {
        "type": "minecraft:crafting_shaped",
        "category": "misc",
        "key": {
          "c": {
            "item": "farmersdelight:pie_crust"
          },
          "e": {
            "tag": "forge:eggs"
          },
          "m": {
            "tag": "forge:milk"
          },
          "o": {
            "tag": "forge:crops/onion"
          },
          "p": {
            "item": "collectorsreap:baked_portobello_cap"
          }
        },
        "pattern": [
          "eme",
          "ooo",
          "pcp"
        ],
        "result": {
          "item": "collectorsreap:portobello_quiche"
        },
        "show_notification": true
      }
    }
  ]
}