{
  "advancements": [
    {
      "advancement": {
        "parent": "minecraft:recipes/root",
        "criteria": {
          "has_lemonade": {
            "conditions": {
              "items": [
                {
                  "items": [
                    "veggiedelight:lemonade"
                  ]
                }
              ]
            },
            "trigger": "minecraft:inventory_changed"
          },
          "has_the_recipe": {
            "conditions": {
              "recipe": "veggiedelight:food/berry_lemonade_from_lemonade"
            },
            "trigger": "minecraft:recipe_unlocked"
          }
        },
        "requirements": [
          [
            "has_lemonade",
            "has_the_recipe"
          ]
        ],
        "rewards": {
          "recipes": [
            "veggiedelight:food/berry_lemonade_from_lemonade"
          ]
        }
      },
      "conditions": [
        {
          "type": "veggiedelight:enabled",
          "value": "berry_lemonade"
        }
      ]
    }
  ]
}